escapepod_sdk/__init__.py
escapepod_sdk/connection.py
escapepod_sdk/events.py
escapepod_sdk/exceptions.py
escapepod_sdk/extension.py
escapepod_sdk/intents.py
escapepod_sdk/messages.py
escapepod_sdk/util.py
escapepod_sdk/version.py
escapepod_sdk/messaging/__init__.py
escapepod_sdk/messaging/client.py
escapepod_sdk/messaging/cybervector_proxy_grpc.py
escapepod_sdk/messaging/cybervector_proxy_pb2.py
escapepod_sdk/messaging/protocol.py
escapepod_sdk-1.0.0.dist-info/LICENSE
escapepod_sdk-1.0.0.dist-info/LICENSE.txt
escapepod_sdk-1.0.0.dist-info/METADATA
escapepod_sdk-1.0.0.dist-info/WHEEL
escapepod_sdk-1.0.0.dist-info/top_level.txt
escapepod_sdk-1.0.0.dist-info/zip-safe
escapepod_sdk-1.0.0.dist-info/RECORD
